pyabelab/__init__.py
pyabelab/dsp.py
pyabelab/logger.py
pyabelab/version.py
pyabelab-0.0.15.dist-info/LICENSE
pyabelab-0.0.15.dist-info/METADATA
pyabelab-0.0.15.dist-info/WHEEL
pyabelab-0.0.15.dist-info/top_level.txt
pyabelab-0.0.15.dist-info/RECORD
