Metadata-Version: 2.1
Name: pyabelab
Version: 0.0.15
Summary: Library that are likely to be used frequently in ABELAB.
Home-page: UNKNOWN
Author: Tomohiro Kioka
Author-email: p9u78sxh@s.okayama-u.ac.jp
Maintainer: Tomohiro Kioka
Maintainer-email: p9u78sxh@s.okayama-u.ac.jp
License: MIT
Platform: UNKNOWN
Classifier: Programming Language :: Python :: 3
Classifier: Programming Language :: Python :: 3.6
Classifier: Programming Language :: Python :: 3.7
Classifier: Programming Language :: Python :: 3.8
Classifier: Programming Language :: Python :: 3.9
Classifier: Programming Language :: Python :: 3 :: Only
Requires-Python: >=3.6
Requires-Dist: numpy
Requires-Dist: scipy
Requires-Dist: librosa
Requires-Dist: pysptk
Requires-Dist: pyworld
